<annotation>
    <folder>VOC2007</folder>
    <filename>00657.png</filename>
    <source>
        <database>My Database</database>
        <annotation>VOC2007</annotation>
        <image>flickr</image>
        <flickrid>NULL</flickrid>
    </source>
    <owner>
        <flickrid>NULL</flickrid>
        <name>Jia</name>
    </owner>
    <size>
        <width>704</width>
        <height>576</height>
        <depth>3</depth>
    </size>
    <segmented>0</segmented>
    <object>
        <name>15</name>
        <pose>Unspecified</pose>
        <truncated>0</truncated>
        <difficult>0</difficult>
        <bndbox>
            <xmin>46</xmin>
            <ymin>450</ymin>
            <xmax>113</xmax>
            <ymax>570</ymax>
        </bndbox>
    </object>
    <object>
        <name>15</name>
        <pose>Unspecified</pose>
        <truncated>0</truncated>
        <difficult>0</difficult>
        <bndbox>
            <xmin>192</xmin>
            <ymin>498</ymin>
            <xmax>242</xmax>
            <ymax>573</ymax>
        </bndbox>
    </object>
    <object>
        <name>15</name>
        <pose>Unspecified</pose>
        <truncated>0</truncated>
        <difficult>0</difficult>
        <bndbox>
            <xmin>299</xmin>
            <ymin>478</ymin>
            <xmax>354</xmax>
            <ymax>573</ymax>
        </bndbox>
    </object>
    <object>
        <name>15</name>
        <pose>Unspecified</pose>
        <truncated>0</truncated>
        <difficult>0</difficult>
        <bndbox>
            <xmin>382</xmin>
            <ymin>497</ymin>
            <xmax>450</xmax>
            <ymax>569</ymax>
        </bndbox>
    </object>
    <object>
        <name>15</name>
        <pose>Unspecified</pose>
        <truncated>0</truncated>
        <difficult>0</difficult>
        <bndbox>
            <xmin>154</xmin>
            <ymin>347</ymin>
            <xmax>194</xmax>
            <ymax>410</ymax>
        </bndbox>
    </object>
    <object>
        <name>15</name>
        <pose>Unspecified</pose>
        <truncated>0</truncated>
        <difficult>0</difficult>
        <bndbox>
            <xmin>184</xmin>
            <ymin>334</ymin>
            <xmax>203</xmax>
            <ymax>398</ymax>
        </bndbox>
    </object>
    <object>
        <name>15</name>
        <pose>Unspecified</pose>
        <truncated>0</truncated>
        <difficult>0</difficult>
        <bndbox>
            <xmin>242</xmin>
            <ymin>339</ymin>
            <xmax>277</xmax>
            <ymax>437</ymax>
        </bndbox>
    </object>
    <object>
        <name>15</name>
        <pose>Unspecified</pose>
        <truncated>0</truncated>
        <difficult>0</difficult>
        <bndbox>
            <xmin>322</xmin>
            <ymin>301</ymin>
            <xmax>345</xmax>
            <ymax>395</ymax>
        </bndbox>
    </object>
    <object>
        <name>15</name>
        <pose>Unspecified</pose>
        <truncated>0</truncated>
        <difficult>0</difficult>
        <bndbox>
            <xmin>273</xmin>
            <ymin>255</ymin>
            <xmax>301</xmax>
            <ymax>290</ymax>
        </bndbox>
    </object>
</annotation>
